{
  "generator-jhipster": {
    "applicationType": "monolith",
    "gitCompany": "",
    "baseName": "prism",
    "packageName": "com.mycompany.myapp",
    "packageFolder": "com/mycompany/myapp",
    "serverPort": 8080,
    "serviceDiscoveryType": "eureka",
    "authenticationType": "jwt",
    "uaaBaseName": "../uaa",
    "cacheProvider": "no",
    "enableHibernateCache": false,
    "websocket": false,
    "databaseType": "mongodb",
    "devDatabaseType": "mongodb",
    "prodDatabaseType": "mongodb",
    "searchEngine": "elasticsearch",
    "enableSwaggerCodegen": false,
    "messageBroker": false,
    "buildTool": "maven",
    "useSass": true,
    "clientPackageManager": "npm",
    "testFrameworks": ["gatling", "cucumber", "protractor"],
    "enableTranslation": true,
    "nativeLanguage": "en",
    "languages": ["en"],
    "clientFramework": "angularX",
    "jhiPrefix": "jhi",
    "jhipsterVersion": "6.9.1",
    "jwtSecretKey": "N2ZhNDk0MTc1MTNjOGRjNDcwMGY4MGQwYzcxMDA1Y2Q2ZTQ0MDk0NWY0NjlhOTE0MDYwNzk2MzQ0N2FjZDAwMWI3ZmRiM2JmYWJkMDA4NmM1OTU2ZTM4OTQ0MTlkYzdmZTljOTExZDNmZTQ2ZWMwOWI3NTNkOGNmMDdkZWRiM2Y=",
    "embeddableLaunchScript": false,
    "clientTheme": "none",
    "creationTimestamp": 1591112906660,
    "entitySuffix": "",
    "dtoSuffix": "DTO",
    "otherModules": [],
    "blueprints": [],
    "prettierJava": true
  },
  "git-provider": "GitHub",
  "git-company": "Kiekhaefer",
  "repository-name": "prism3"
}
